[
  {
    "Date": "01.10.2024",
    "LP 95": "377.00",
    "LP 92": "311.00",
    "LAD": "283.00",
    "LSD": "319.00",
    "LK": "183.00",
    "LIK": "210.00",
    "FUR. 800": "199.00",
    "FUR 1500 (High)": "199.00",
    "FUR. 1500 (Low)": "199.00"
  },
  {
    "Date": "05.09.2024",
    "LP 95": "377.00",
    "LP 92": "332.00",
    "LAD": "307.00",
    "LSD": "352.00",
    "LK": "202.00",
    "LIK": "210.00",
    "FUR. 800": "199.00",
    "FUR 1500 (High)": "199.00",
    "FUR. 1500 (Low)": "199.00"
  },
  {
    "Date": "01.09.2024",
    "LP 95": "377.00",
    "LP 92": "332.00",
    "LAD": "307.00",
    "LSD": "352.00",
    "LK": "202.00",
    "LIK": "210.00",
    "FUR. 800": "204.00",
    "FUR 1500 (High)": "204.00",
    "FUR. 1500 (Low)": "204.00"
  },
  {
    "Date": "15.07.2024",
    "LP 95": "379.00",
    "LP 92": "344.00",
    "LAD": "317.00",
    "LSD": "355.00",
    "LK": "202.00",
    "LIK": "219.00",
    "FUR. 800": "199.00",
    "FUR 1500 (High)": "199.00",
    "FUR. 1500 (Low)": "199.00"
  },
  {
    "Date": "01.07.2024",
    "LP 95": "379.00",
    "LP 92": "344.00",
    "LAD": "317.00",
    "LSD": "355.00",
    "LK": "202.00",
    "LIK": "210.00",
    "FUR. 800": "204.00",
    "FUR 1500 (High)": "204.00",
    "FUR. 1500 (Low)": "204.00"
  },
  {
    "Date": "05.06.2024",
    "LP 95": "420.00",
    "LP 92": "355.00",
    "LAD": "317.00",
    "LSD": "377.00",
    "LK": "202.00",
    "LIK": "210.00",
    "FUR. 800": "204.00",
    "FUR 1500 (High)": "204.00",
    "FUR. 1500 (Low)": "204.00"
  },
  {
    "Date": "31.05.2024",
    "LP 95": "420.00",
    "LP 92": "355.00",
    "LAD": "317.00",
    "LSD": "377.00",
    "LK": "202.00",
    "LIK": "223.00",
    "FUR. 800": "204.00",
    "FUR 1500 (High)": "204.00",
    "FUR. 1500 (Low)": "204.00"
  },
  {
    "Date": "06.05.2024",
    "LP 95": "420.00",
    "LP 92": "368.00",
    "LAD": "333.00",
    "LSD": "377.00",
    "LK": "215.00",
    "LIK": "223.00",
    "FUR. 800": "204.00",
    "FUR 1500 (High)": "204.00",
    "FUR. 1500 (Low)": "204.00"
  },
  {
    "Date": "05.04.2024",
    "LP 95": "420.00",
    "LP 92": "368.00",
    "LAD": "333.00",
    "LSD": "377.00",
    "LK": "215.00",
    "LIK": "250.00",
    "FUR. 800": "204.00",
    "FUR 1500 (High)": "204.00",
    "FUR. 1500 (Low)": "204.00"
  },
  {
    "Date": "30.04.2024",
    "LP 95": "420.00",
    "LP 92": "368.00",
    "LAD": "333.00",
    "LSD": "377.00",
    "LK": "215.00",
    "LIK": "260.00",
    "FUR. 800": "204.00",
    "FUR 1500 (High)": "204.00",
    "FUR. 1500 (Low)": "204.00"
  },
  {
    "Date": "06.04.2024",
    "LP 95": "440.00",
    "LP 92": "371.00",
    "LAD": "363.00",
    "LSD": "386.00",
    "LK": "245.00",
    "LIK": "260.00",
    "FUR. 800": "189.00",
    "FUR 1500 (High)": "189.00",
    "FUR. 1500 (Low)": "189.00"
  },
  {
    "Date": "01.04.2024",
    "LP 95": "440.00",
    "LP 92": "371.00",
    "LAD": "363.00",
    "LSD": "386.00",
    "LK": "245.00",
    "LIK": "260.00",
    "FUR. 800": "204.00",
    "FUR 1500 (High)": "204.00",
    "FUR. 1500 (Low)": "204.00"
  },
  {
    "Date": "05.03.2024",
    "LP 95": "447.00",
    "LP 92": "371.00",
    "LAD": "363.00",
    "LSD": "458.00",
    "LK": "257.00",
    "LIK": "260.00",
    "FUR. 800": "204.00",
    "FUR 1500 (High)": "204.00",
    "FUR. 1500 (Low)": "204.00"
  },
  {
    "Date": "01.02.2024",
    "LP 95": "456.00",
    "LP 92": "371.00",
    "LAD": "363.00",
    "LSD": "468.00",
    "LK": "262.00",
    "LIK": "266.00",
    "FUR. 800": "201.00",
    "FUR 1500 (High)": "201.00",
    "FUR. 1500 (Low)": "201.00"
  },
  {
    "Date": "01.01.2024",
    "LP 95": "464.00",
    "LP 92": "366.00",
    "LAD": "358.00",
    "LSD": "475.00",
    "LK": "236.00",
    "LIK": "251.00",
    "FUR. 800": "211.00",
    "FUR 1500 (High)": "211.00",
    "FUR. 1500 (Low)": "211.00"
  },
  {
    "Date": "01.12.2023",
    "LP 95": "426.00",
    "LP 92": "346.00",
    "LAD": "329.00",
    "LSD": "434.00",
    "LK": "247.00",
    "LIK": "288.00",
    "FUR. 800": "207.00",
    "FUR 1500 (High)": "207.00",
    "FUR. 1500 (Low)": "207.00"
  },
  {
    "Date": "01.11.2023",
    "LP 95": "423.00",
    "LP 92": "356.00",
    "LAD": "356.00",
    "LSD": "431.00",
    "LK": "249.00",
    "LIK": "288.00",
    "FUR. 800": "207.00",
    "FUR 1500 (High)": "207.00",
    "FUR. 1500 (Low)": "207.00"
  },
  {
    "Date": "02.10.2023",
    "LP 95": "420.00",
    "LP 92": "365.00",
    "LAD": "351.00",
    "LSD": "421.00",
    "LK": "242.00",
    "LIK": "300.00",
    "FUR. 800": "191.00",
    "FUR 1500 (High)": "191.00",
    "FUR. 1500 (Low)": "191.00"
  },
  {
    "Date": "01.09.2023",
    "LP 95": "417.00",
    "LP 92": "361.00",
    "LAD": "341.00",
    "LSD": "359.00",
    "LK": "231.00",
    "LIK": "238.00",
    "FUR. 800": "191.00",
    "FUR 1500 (High)": "191.00",
    "FUR. 1500 (Low)": "191.00"
  },
  {
    "Date": "01.08.2023",
    "LP 95": "375.00",
    "LP 92": "348.00",
    "LAD": "306.00",
    "LSD": "358.00",
    "LK": "226.00",
    "LIK": "231.00",
    "FUR. 800": "203.00",
    "FUR 1500 (High)": "203.00",
    "FUR. 1500 (Low)": "203.00"
  },
  {
    "Date": "01.07.2023",
    "LP 95": "365.00",
    "LP 92": "328.00",
    "LAD": "308.00",
    "LSD": "346.00",
    "LK": "236.00",
    "LIK": "270.00",
    "FUR. 800": "216.00",
    "FUR 1500 (High)": "216.00",
    "FUR. 1500 (Low)": "216.00"
  },
  {
    "Date": "01.06.2023",
    "LP 95": "385.00",
    "LP 92": "318.00",
    "LAD": "310.00",
    "LSD": "340.00",
    "LK": "245.00",
    "LIK": "270.00",
    "FUR. 800": "216.00",
    "FUR 1500 (High)": "216.00",
    "FUR. 1500 (Low)": "216.00"
  },
  {
    "Date": "01.05.2023",
    "LP 95": "365.00",
    "LP 92": "333.00",
    "LAD": "310.00",
    "LSD": "330.00",
    "LK": "295.00",
    "LIK": "330.00",
    "FUR. 800": "261.00",
    "FUR 1500 (High)": "261.00",
    "FUR. 1500 (Low)": "261.00"
  },
  {
    "Date": "30.03.2023",
    "LP 95": "375.00",
    "LP 92": "340.00",
    "LAD": "325.00",
    "LSD": "465.00",
    "LK": "295.00",
    "LIK": "330.00",
    "FUR. 800": "320.00",
    "FUR 1500 (High)": "320.00",
    "FUR. 1500 (Low)": "320.00"
  },
  {
    "Date": "02.03.2023",
    "LP 95": "510.00",
    "LP 92": "400.00",
    "LAD": "405.00",
    "LSD": "510.00",
    "LK": "305.00",
    "LIK": "330.00",
    "FUR. 800": "320.00",
    "FUR 1500 (High)": "320.00",
    "FUR. 1500 (Low)": "320.00"
  },
  {
    "Date": "01.02.2023",
    "LP 95": "510.00",
    "LP 92": "400.00",
    "LAD": "405.00",
    "LSD": "510.00",
    "LK": "355.00",
    "LIK": "464.00",
    "FUR. 800": "320.00",
    "FUR 1500 (High)": "320.00",
    "FUR. 1500 (Low)": "320.00"
  },
  {
    "Date": "03.01.2023",
    "LP 95": "510.00",
    "LP 92": "370.00",
    "LAD": "405.00",
    "LSD": "510.00",
    "LK": "355.00",
    "LIK": "464.00",
    "FUR. 800": "320.00",
    "FUR 1500 (High)": "320.00",
    "FUR. 1500 (Low)": "320.00"
  },
  {
    "Date": "06.12.2022",
    "LP 95": "510.00",
    "LP 92": "370.00",
    "LAD": "420.00",
    "LSD": "510.00",
    "LK": "365.00",
    "LIK": "464.00",
    "FUR. 800": "320.00",
    "FUR 1500 (High)": "320.00",
    "FUR. 1500 (Low)": "320.00"
  },
  {
    "Date": "12.11.2022",
    "LP 95": "510.00",
    "LP 92": "370.00",
    "LAD": "430.00",
    "LSD": "510.00",
    "LK": "365.00",
    "LIK": "464.00",
    "FUR. 800": "419.00",
    "FUR 1500 (High)": "419.00",
    "FUR. 1500 (Low)": "419.00"
  },
  {
    "Date": "17.10.2022",
    "LP 95": "510.00",
    "LP 92": "370.00",
    "LAD": "415.00",
    "LSD": "510.00",
    "LK": "340.00",
    "LIK": "464.00",
    "FUR. 800": "320.00",
    "FUR 1500 (High)": "320.00",
    "FUR. 1500 (Low)": "320.00"
  },
  {
    "Date": "17.10.2022(9.00 PM)",
    "LP 95": "510.00",
    "LP 92": "370.00",
    "LAD": "415.00",
    "LSD": "510.00",
    "LK": "340.00",
    "LIK": "464.00",
    "FUR. 800": "419.00",
    "FUR 1500 (High)": "419.00",
    "FUR. 1500 (Low)": "419.00"
  },
  {
    "Date": "02.10.2022",
    "LP 95": "510.00",
    "LP 92": "410.00",
    "LAD": "430.00",
    "LSD": "510.00",
    "LK": "340.00",
    "LIK": "464.00",
    "FUR. 800": "419.00",
    "FUR 1500 (High)": "419.00",
    "FUR. 1500 (Low)": "419.00"
  },
  {
    "Date": "21.08.2022",
    "LP 95": "540.00",
    "LP 92": "450.00",
    "LAD": "430.00",
    "LSD": "510.00",
    "LK": "340.00",
    "LIK": "464.00",
    "FUR. 800": "419.00",
    "FUR 1500 (High)": "419.00",
    "FUR. 1500 (Low)": "419.00"
  },
  {
    "Date": "01.08.2022",
    "LP 95": "540.00",
    "LP 92": "450.00",
    "LAD": "430.00",
    "LSD": "510.00",
    "LK": "87.00",
    "LIK": "464.00",
    "FUR. 800": "419.00",
    "FUR 1500 (High)": "419.00",
    "FUR. 1500 (Low)": "419.00"
  },
  {
    "Date": "17.07.2022",
    "LP 95": "540.00",
    "LP 92": "450.00",
    "LAD": "440.00",
    "LSD": "510.00",
    "LK": "87.00",
    "LIK": "464.00",
    "FUR. 800": "419.00",
    "FUR 1500 (High)": "419.00",
    "FUR. 1500 (Low)": "419.00"
  },
  {
    "Date": "26.06.2022",
    "LP 95": "550.00",
    "LP 92": "470.00",
    "LAD": "460.00",
    "LSD": "520.00",
    "LK": "87.00",
    "LIK": "464.00",
    "FUR. 800": "419.00",
    "FUR 1500 (High)": "419.00",
    "FUR. 1500 (Low)": "419.00"
  },
  {
    "Date": "24.05.2022",
    "LP 95": "450.00",
    "LP 92": "420.00",
    "LAD": "400.00",
    "LSD": "445.00",
    "LK": "87.00",
    "LIK": "399.00",
    "FUR. 800": "369.00",
    "FUR 1500 (High)": "369.00",
    "FUR. 1500 (Low)": "369.00"
  },
  {
    "Date": "22.04.2022",
    "LP 95": "373.00",
    "LP 92": "338.00",
    "LAD": "289.00",
    "LSD": "329.00",
    "LK": "87.00",
    "LIK": "305.00",
    "FUR. 800": "289.00",
    "FUR 1500 (High)": "289.00",
    "FUR. 1500 (Low)": "289.00"
  },
  {
    "Date": "18.04.2022",
    "LP 95": "373.00",
    "LP 92": "338.00",
    "LAD": "289.00",
    "LSD": "329.00",
    "LK": "87.00",
    "LIK": "160.00",
    "FUR. 800": "214.00",
    "FUR 1500 (High)": "214.00",
    "FUR. 1500 (Low)": "214.00"
  },
  {
    "Date": "22.03.2022",
    "LP 95": "283.00",
    "LP 92": "254.00",
    "LAD": "176.00",
    "LSD": "254.00",
    "LK": "87.00",
    "LIK": "160.00",
    "FUR. 800": "214.00",
    "FUR 1500 (High)": "214.00",
    "FUR. 1500 (Low)": "214.00"
  },
  {
    "Date": "11.03.2022",
    "LP 95": "283.00",
    "LP 92": "254.00",
    "LAD": "176.00",
    "LSD": "254.00",
    "LK": "87.00",
    "LIK": "110.00",
    "FUR. 800": "214.00",
    "FUR 1500 (High)": "214.00",
    "FUR. 1500 (Low)": "214.00"
  },
  {
    "Date": "27.12.2021",
    "LP 95": "207.00",
    "LP 92": "177.00",
    "LAD": "121.00",
    "LSD": "159.00",
    "LK": "87.00",
    "LIK": "110.00",
    "FUR. 800": "110.00",
    "FUR 1500 (High)": "110.00",
    "FUR. 1500 (Low)": "110.00"
  },
  {
    "Date": "20.12.2021",
    "LP 95": "207.00",
    "LP 92": "177.00",
    "LAD": "121.00",
    "LSD": "159.00",
    "LK": "87.00",
    "LIK": "110.00",
    "FUR. 800": "92.00",
    "FUR 1500 (High)": "96.00",
    "FUR. 1500 (Low)": "96.00"
  },
  {
    "Date": "11.06.2021",
    "LP 95": "184.00",
    "LP 92": "157.00",
    "LAD": "111.00",
    "LSD": "144.00",
    "LK": "77.00",
    "LIK": "110.00",
    "FUR. 800": "92.00",
    "FUR 1500 (High)": "96.00",
    "FUR. 1500 (Low)": "96.00"
  },
  {
    "Date": "10.09.2019",
    "LP 95": "161.00",
    "LP 92": "137.00",
    "LAD": "104.00",
    "LSD": "132.00",
    "LK": "70.00",
    "LIK": "110.00",
    "FUR. 800": "92.00",
    "FUR 1500 (High)": "96.00",
    "FUR. 1500 (Low)": "96.00"
  },
  {
    "Date": "13.08.2019",
    "LP 95": "163.00",
    "LP 92": "138.00",
    "LAD": "104.00",
    "LSD": "134.00",
    "LK": "70.00",
    "LIK": "110.00",
    "FUR. 800": "92.00",
    "FUR 1500 (High)": "96.00",
    "FUR. 1500 (Low)": "96.00"
  },
  {
    "Date": "11.07.2019",
    "LP 95": "159.00",
    "LP 92": "136.00",
    "LAD": "104.00",
    "LSD": "131.00",
    "LK": "70.00",
    "LIK": "110.00",
    "FUR. 800": "92.00",
    "FUR 1500 (High)": "96.00",
    "FUR. 1500 (Low)": "96.00"
  },
  {
    "Date": "11.06.2019",
    "LP 95": "164.00",
    "LP 92": "138.00",
    "LAD": "104.00",
    "LSD": "136.00",
    "LK": "70.00",
    "LIK": "110.00",
    "FUR. 800": "92.00",
    "FUR 1500 (High)": "96.00",
    "FUR. 1500 (Low)": "96.00"
  },
  {
    "Date": "11.05.2019",
    "LP 95": "164.00",
    "LP 92": "135.00",
    "LAD": "104.00",
    "LSD": "136.00",
    "LK": "70.00",
    "LIK": "110.00",
    "FUR. 800": "92.00",
    "FUR 1500 (High)": "96.00",
    "FUR. 1500 (Low)": "96.00"
  },
  {
    "Date": "13.03.2019",
    "LP 95": "159.00",
    "LP 92": "132.00",
    "LAD": "104.00",
    "LSD": "134.00",
    "LK": "70.00",
    "LIK": "110.00",
    "FUR. 800": "92.00",
    "FUR 1500 (High)": "96.00",
    "FUR. 1500 (Low)": "96.00"
  },
  {
    "Date": "12.02.2019",
    "LP 95": "152.00",
    "LP 92": "129.00",
    "LAD": "103.00",
    "LSD": "126.00",
    "LK": "70.00",
    "LIK": "110.00",
    "FUR. 800": "92.00",
    "FUR 1500 (High)": "96.00",
    "FUR. 1500 (Low)": "96.00"
  },
  {
    "Date": "11.01.2019",
    "LP 95": "147.00",
    "LP 92": "123.00",
    "LAD": "99.00",
    "LSD": "118.00",
    "LK": "70.00",
    "LIK": "110.00",
    "FUR. 800": "92.00",
    "FUR 1500 (High)": "96.00",
    "FUR. 1500 (Low)": "96.00"
  },
  {
    "Date": "22.12.2018",
    "LP 95": "149.00",
    "LP 92": "125.00",
    "LAD": "101.00",
    "LSD": "121.00",
    "LK": "70.00",
    "LIK": "110.00",
    "FUR. 800": "92.00",
    "FUR 1500 (High)": "96.00",
    "FUR. 1500 (Low)": "96.00"
  },
  {
    "Date": "01.12.2018",
    "LP 95": "159.00",
    "LP 92": "135.00",
    "LAD": "106.00",
    "LSD": "131.00",
    "LK": "70.00",
    "LIK": "110.00",
    "FUR. 800": "92.00",
    "FUR 1500 (High)": "96.00",
    "FUR. 1500 (Low)": "96.00"
  },
  {
    "Date": "16.11.2018",
    "LP 95": "164.00",
    "LP 92": "140.00",
    "LAD": "111.00",
    "LSD": "136.00",
    "LK": "70.00",
    "LIK": "110.00",
    "FUR. 800": "92.00",
    "FUR 1500 (High)": "96.00",
    "FUR. 1500 (Low)": "96.00"
  },
  {
    "Date": "02.11.2018",
    "LP 95": "169.00",
    "LP 92": "145.00",
    "LAD": "116.00",
    "LSD": "141.00",
    "LK": "70.00",
    "LIK": "110",
    "FUR. 800": "92.00",
    "FUR 1500 (High)": "96.00",
    "FUR. 1500 (Low)": "96.00"
  },
  {
    "Date": "11.10.2018",
    "LP 95": "169.00",
    "LP 92": "155.00",
    "LAD": "123.00",
    "LSD": "141.00",
    "LK": "70.00",
    "LIK": "110.00",
    "FUR. 800": "92.00",
    "FUR 1500 (High)": "96.00",
    "FUR. 1500 (Low)": "96.00"
  },
  {
    "Date": "11.09.2018",
    "LP 95": "161.00",
    "LP 92": "149.00",
    "LAD": "123.00",
    "LSD": "133.00",
    "LK": "70.00",
    "LIK": "110.00",
    "FUR. 800": "92.00",
    "FUR 1500 (High)": "96.00",
    "FUR. 1500 (Low)": "96.00"
  },
  {
    "Date": "04.09.2018",
    "LP 95": "157.00",
    "LP 92": "145.00",
    "LAD": "118.00",
    "LSD": "130.00",
    "LK": "70.00",
    "LIK": "110.00",
    "FUR. 800": "92.00",
    "FUR 1500 (High)": "96.00",
    "FUR. 1500 (Low)": "96.00"
  },
  {
    "Date": "11.08.2018",
    "LP 95": "157.00",
    "LP 92": "145.00",
    "LAD": "118.00",
    "LSD": "130.00",
    "LK": "70.00",
    "LIK": "110.00",
    "FUR. 800": "82.20",
    "FUR 1500 (High)": "80.00",
    "FUR. 1500 (Low)": "90.00"
  },
  {
    "Date": "11.07.2018",
    "LP 95": "155.00",
    "LP 92": "145.00",
    "LAD": "118.00",
    "LSD": "129.00",
    "LK": "70.00",
    "LIK": "110.00",
    "FUR. 800": "82.20",
    "FUR 1500 (High)": "80.00",
    "FUR. 1500 (Low)": "90.00"
  },
  {
    "Date": "13.06.2018",
    "LP 95": "148.00",
    "LP 92": "137.00",
    "LAD": "109.00",
    "LSD": "119.00",
    "LK": "70.00",
    "LIK": "110.00",
    "FUR. 800": "82.20",
    "FUR 1500 (High)": "80.00",
    "FUR. 1500 (Low)": "90.00"
  },
  {
    "Date": "11.05.2018",
    "LP 95": "148.00",
    "LP 92": "137.00.00",
    "LAD": "109.00",
    "LSD": "119.00",
    "LK": "101.00",
    "LIK": "110.00",
    "FUR. 800": "82.20",
    "FUR 1500 (High)": "80.00",
    "FUR. 1500 (Low)": "90.00"
  },
  {
    "Date": "28.11.2015",
    "LP 95": "128.00",
    "LP 92": "117.00",
    "LAD": "95.00",
    "LSD": "110.00",
    "LK": "49.00",
    "LIK": "88.00",
    "FUR. 800": "82.20",
    "FUR 1500 (High)": "80.00",
    "FUR. 1500 (Low)": "90.00"
  },
  {
    "Date": "29.01.2015",
    "LP 95": "128.00",
    "LP 92": "117.00",
    "LAD": "95.00",
    "LSD": "110.00",
    "LK": "59.00",
    "LIK": "88.00",
    "FUR. 800": "82.20",
    "FUR 1500 (High)": "80.00",
    "FUR. 1500 (Low)": "90.00"
  },
  {
    "Date": "22.01.2015",
    "LP 95": "128.00",
    "LP 92": "117.00",
    "LAD": "95.00",
    "LSD": "110.00",
    "LK": "65.00",
    "LIK": "94.00",
    "FUR. 800": "82.20",
    "FUR 1500 (High)": "80.00",
    "FUR. 1500 (Low)": "90.00"
  },
  {
    "Date": "01.01.2015",
    "LP 95": "158.00",
    "LP 92": "150.00",
    "LAD": "111.00",
    "LSD": "133.00",
    "LK": "81.00",
    "LIK": "110.00",
    "FUR. 800": "82.20",
    "FUR 1500 (High)": "80.00",
    "FUR. 1500 (Low)": "90.00"
  },
  {
    "Date": "05.12.2014",
    "LP 95": "158.00",
    "LP 92": "150.00",
    "LAD": "111.00",
    "LSD": "133.00",
    "LK": "81.00",
    "LIK": "110.00",
    "FUR. 800": "92.20",
    "FUR 1500 (High)": "",
    "FUR. 1500 (Low)": "90.00"
  },
  {
    "Date": "17.09.2014",
    "LP 95": "165.00",
    "LP 92": "157.00",
    "LAD": "118.00",
    "LSD": "140.00",
    "LK": "86.00",
    "LIK": "115.00",
    "FUR. 800": "92.20",
    "FUR 1500 (High)": "",
    "FUR. 1500 (Low)": "90.00"
  },
  {
    "Date": "23.02.2013",
    "LP 95": "170.00",
    "LP 92": "162.00",
    "LAD": "121.00",
    "LSD": "145.00",
    "LK": "106.00",
    "LIK": "115.00",
    "FUR. 800": "92.20",
    "FUR 1500 (High)": "",
    "FUR. 1500 (Low)": "90.00"
  },
  {
    "Date": "14.12.2012",
    "LP 95": "167.00",
    "LP 92": "159.00",
    "LAD": "115.00",
    "LSD": "142.00",
    "LK": "106.00",
    "LIK": "111.00",
    "FUR. 800": "92.20",
    "FUR 1500 (High)": "",
    "FUR. 1500 (Low)": "90.00"
  },
  {
    "Date": "12.02.2012",
    "LP 95": "167.00",
    "LP 92": "149.00",
    "LAD": "115.00",
    "LSD": "142.00",
    "LK": "106.00",
    "LIK": "111.00",
    "FUR. 800": "92.20",
    "FUR 1500 (High)": "",
    "FUR. 1500 (Low)": "90.00"
  },
  {
    "Date": "30.10.2011",
    "LP 95": "155.00",
    "LP 92": "137.00",
    "LAD": "84.00",
    "LSD": "106.30",
    "LK": "71.00",
    "LIK": "76.00",
    "FUR. 800": "52.20",
    "FUR 1500 (High)": "",
    "FUR. 1500 (Low)": "50.00"
  },
  {
    "Date": "01.04.2011",
    "LP 95": "143.00",
    "LP 92": "125.00",
    "LAD": "76.00",
    "LSD": "98.30",
    "LK": "61.00",
    "LIK": "66.00",
    "FUR. 800": "52.20",
    "FUR 1500 (High)": "",
    "FUR. 1500 (Low)": "50.00"
  },
  {
    "Date": "01.09.2010",
    "LP 95": "133.00",
    "LP 92": "115.00",
    "LAD": "73.00",
    "LSD": "88.30",
    "LK": "51.00",
    "LIK": "56.00",
    "FUR. 800": "42.20",
    "FUR 1500 (High)": "",
    "FUR. 1500 (Low)": "40.00"
  },
  {
    "Date": "29.12.2009",
    "LP 95": "133.00",
    "LP 92": "115.00",
    "LAD": "73.00",
    "LSD": "88.30",
    "LK": "51.00",
    "LIK": "56.00",
    "FUR. 800": "32.90",
    "FUR 1500 (High)": "",
    "FUR. 1500 (Low)": "32.70"
  },
  {
    "Date": "02.07.2009",
    "LP 95": "148.00",
    "LP 92": "130.00",
    "LAD": "73.00",
    "LSD": "88.30",
    "LK": "51.00",
    "LIK": "56.00",
    "FUR. 800": "34.90",
    "FUR 1500 (High)": "",
    "FUR. 1500 (Low)": "32.70"
  },
  {
    "Date": "30.12.2008",
    "LP 95": "133.00",
    "LP 92": "120.00",
    "LAD": "70.00",
    "LSD": "85.30",
    "LK": "50.00",
    "LIK": "55.00",
    "FUR. 800": "33.90",
    "FUR 1500 (High)": "",
    "FUR. 1500 (Low)": "25.00"
  },
  {
    "Date": "06.12.2008",
    "LP 95": "135.00",
    "LP 92": "122.00",
    "LAD": "80.00",
    "LSD": "95.30",
    "LK": "60.00",
    "LIK": "65.00",
    "FUR. 800": "53.9.00",
    "FUR 1500 (High)": "",
    "FUR. 1500 (Low)": "51.70"
  },
  {
    "Date": "07.11.2008",
    "LP 95": "155.00",
    "LP 92": "142.00",
    "LAD": "80.00",
    "LSD": "95.30",
    "LK": "60.00",
    "LIK": "65.00",
    "FUR. 800": "53.90",
    "FUR 1500 (High)": "",
    "FUR. 1500 (Low)": "51.70"
  },
  {
    "Date": "25.05.2008",
    "LP 95": "170.00",
    "LP 92": "157.00",
    "LAD": "110.00",
    "LSD": "125.30",
    "LK": "80.00",
    "LIK": "85.00",
    "FUR. 800": "63.90",
    "FUR 1500 (High)": "",
    "FUR. 1500 (Low)": "61.70"
  },
  {
    "Date": "14.01.2008",
    "LP 95": "130.00",
    "LP 92": "127.00",
    "LAD": "80.00",
    "LSD": "85.30",
    "LK": "70.00",
    "LIK": "75.00",
    "FUR. 800": "63.90",
    "FUR 1500 (High)": "",
    "FUR. 1500 (Low)": "61.70"
  },
  {
    "Date": "29.07.2007",
    "LP 95": "120.00",
    "LP 92": "117.00",
    "LAD": "75.00",
    "LSD": "80.30",
    "LK": "68.00",
    "LIK": "69.00",
    "FUR. 800": "53.90",
    "FUR 1500 (High)": "",
    "FUR. 1500 (Low)": "51.70"
  },
  {
    "Date": "30.06.2007",
    "LP 95": "114.00",
    "LP 92": "111.00",
    "LAD": "71.00",
    "LSD": "76.30",
    "LK": "67.00",
    "LIK": "68.00",
    "FUR. 800": "49.90",
    "FUR 1500 (High)": "",
    "FUR. 1500 (Low)": "47.70"
  },
  {
    "Date": "12.05.2007",
    "LP 95": "109.00",
    "LP 92": "106.00",
    "LAD": "67.00",
    "LSD": "72.30",
    "LK": "51.00",
    "LIK": "61.30",
    "FUR. 800": "45.90",
    "FUR 1500 (High)": "",
    "FUR. 1500 (Low)": "43.70"
  },
  {
    "Date": "28.04.2007",
    "LP 95": "108.00",
    "LP 92": "105.00",
    "LAD": "65.00",
    "LSD": "70.30",
    "LK": "50.00",
    "LIK": "60.30",
    "FUR. 800": "39.90",
    "FUR 1500 (High)": "",
    "FUR. 1500 (Low)": "37.30"
  },
  {
    "Date": "19.04.2007",
    "LP 95": "107.00",
    "LP 92": "104.00",
    "LAD": "63.0",
    "LSD": "68.30",
    "LK": "48.00",
    "LIK": "60.30",
    "FUR. 800": "39.90",
    "FUR 1500 (High)": "",
    "FUR. 1500 (Low)": "37.30"
  },
  {
    "Date": "05.01.2007",
    "LP 95": "97.00",
    "LP 92": "100.00",
    "LAD": "60.00",
    "LSD": "65.30",
    "LK": "48.00",
    "LIK": "58.30",
    "FUR. 800": "45.80",
    "FUR 1500 (High)": "",
    "FUR. 1500 (Low)": "37.70"
  },
  {
    "Date": "01.01.2007",
    "LP 95": "95.00",
    "LP 92": "92.00",
    "LAD": "60.00",
    "LSD": "65.30",
    "LK": "48.00",
    "LIK": "58.30",
    "FUR. 800": "45.80",
    "FUR 1500 (High)": "",
    "FUR. 1500 (Low)": "37.70"
  },
  {
    "Date": "27.12.2006",
    "LP 95": "95.00",
    "LP 92": "92.00",
    "LAD": "60.00",
    "LSD": "65.30",
    "LK": "48.00",
    "LIK": "58.30",
    "FUR. 800": "45.80",
    "FUR 1500 (High)": "",
    "FUR. 1500 (Low)": "43.30"
  },
  {
    "Date": "26.10.2006",
    "LP 95": "95.00",
    "LP 92": "92.00",
    "LAD": "60.00",
    "LSD": "65.30",
    "LK": "48.00",
    "LIK": "50.30",
    "FUR. 800": "45.80",
    "FUR 1500 (High)": "",
    "FUR. 1500 (Low)": "43.30"
  },
  {
    "Date": "02.08.2006",
    "LP 95": "99.00",
    "LP 92": "96.00",
    "LAD": "64.00",
    "LSD": "69.30",
    "LK": "45.50",
    "LIK": "47.80",
    "FUR. 800": "47.80",
    "FUR 1500 (High)": "",
    "FUR. 1500 (Low)": "45.30"
  },
  {
    "Date": "11.06.2006",
    "LP 95": "96.00",
    "LP 92": "93.00",
    "LAD": "61.00",
    "LSD": "68.30",
    "LK": "43.50",
    "LIK": "45.80",
    "FUR. 800": "45.80",
    "FUR 1500 (High)": "",
    "FUR. 1500 (Low)": "43.30"
  },
  {
    "Date": "16.04.2006",
    "LP 95": "91.00",
    "LP 92": "88.00",
    "LAD": "58.00",
    "LSD": "63.30",
    "LK": "38.50",
    "LIK": "40.80",
    "FUR. 800": "40.80",
    "FUR 1500 (High)": "",
    "FUR. 1500 (Low)": "38.30"
  },
  {
    "Date": "16.04.2006",
    "LP 95": "91.00",
    "LP 92": "88.00",
    "LAD": "58.00",
    "LSD": "63.30",
    "LK": "38.50",
    "LIK": "40.80",
    "FUR. 800": "40.80",
    "FUR 1500 (High)": "",
    "FUR. 1500 (Low)": "38.30"
  },
  {
    "Date": "06.06.2005",
    "LP 95": "83.00",
    "LP 92": "80.00",
    "LAD": "50.00",
    "LSD": "55.30",
    "LK": "30.50",
    "LIK": "32.80",
    "FUR. 800": "32.80",
    "FUR 1500 (High)": "",
    "FUR. 1500 (Low)": "30.30"
  },
  {
    "Date": "05.05.2005",
    "LP 95": "77.00",
    "LP 92": "74.00",
    "LAD": "46.00",
    "LSD": "51.30",
    "LK": "28.50",
    "LIK": "30.80",
    "FUR. 800": "30.30",
    "FUR 1500 (High)": "",
    "FUR. 1500 (Low)": "28.30"
  },
  {
    "Date": "25.09.2004",
    "LP 95": "73.00",
    "LP 92": "70.00",
    "LAD": "44.00",
    "LSD": "49.30",
    "LK": "25.50",
    "LIK": "27.80",
    "FUR. 800": "25.20",
    "FUR 1500 (High)": "",
    "FUR. 1500 (Low)": "24.30"
  },
  {
    "Date": "13.08.2004",
    "LP 95": "71.00",
    "LP 92": "68.00",
    "LAD": "36.00",
    "LSD": "41.30",
    "LK": "25.50",
    "LIK": "27.80",
    "FUR. 800": "25.20",
    "FUR 1500 (High)": "",
    "FUR. 1500 (Low)": "24.30"
  },
  {
    "Date": "23.07.2004",
    "LP 95": "68.00",
    "LP 92": "65.00",
    "LAD": "32.0",
    "LSD": "37.50",
    "LK": "25.50",
    "LIK": "27.80",
    "FUR. 800": "24.70",
    "FUR 1500 (High)": "",
    "FUR. 1500 (Low)": "23.30"
  },
  {
    "Date": "12.02.2004",
    "LP 95": "60.00",
    "LP 92": "57.00",
    "LAD": "32.00",
    "LSD": "37.50",
    "LK": "25.50",
    "LIK": "27.80",
    "FUR. 800": "24.70",
    "FUR 1500 (High)": "",
    "FUR. 1500 (Low)": "23.30"
  },
  {
    "Date": "25.01.2004",
    "LP 95": "58.00",
    "LP 92": "55.00",
    "LAD": "32.00",
    "LSD": "37.50",
    "LK": "25.50",
    "LIK": "27.80",
    "FUR. 800": "23.70",
    "FUR 1500 (High)": "",
    "FUR. 1500 (Low)": "22.30"
  },
  {
    "Date": "04.12.2003",
    "LP 95": "56.00",
    "LP 92": "53.00",
    "LAD": "32.00",
    "LSD": "37.30",
    "LK": "25.50",
    "LIK": "27.80",
    "FUR. 800": "23.70",
    "FUR 1500 (High)": "",
    "FUR. 1500 (Low)": "22.30"
  },
  {
    "Date": "11.11.2003",
    "LP 95": "56.00",
    "LP 92": "53.00",
    "LAD": "31.00",
    "LSD": "36.30",
    "LK": "23.50",
    "LIK": "25.80",
    "FUR. 800": "23.50",
    "FUR 1500 (High)": "",
    "FUR. 1500 (Low)": "22.20"
  },
  {
    "Date": "05.10.2003",
    "LP 95": "55.00",
    "LP 92": "52.00",
    "LAD": "30.50",
    "LSD": "35.80",
    "LK": "23.00",
    "LIK": "25.30",
    "FUR. 800": "23.10",
    "FUR 1500 (High)": "",
    "FUR. 1500 (Low)": "21.80"
  },
  {
    "Date": "04.09.2003",
    "LP 95": "57.00",
    "LP 92": "54.00",
    "LAD": "31.50",
    "LSD": "36.80",
    "LK": "25.00",
    "LIK": "27.30",
    "FUR. 800": "24.30",
    "FUR 1500 (High)": "",
    "FUR. 1500 (Low)": "23.10"
  },
  {
    "Date": "07.08.2003",
    "LP 95": "55.00",
    "LP 92": "52.00",
    "LAD": "30.00",
    "LSD": "35.30",
    "LK": "24.00",
    "LIK": "26.30",
    "FUR. 800": "24.90",
    "FUR 1500 (High)": "",
    "FUR. 1500 (Low)": "24.20"
  },
  {
    "Date": "30.06.2003",
    "LP 95": "55.00",
    "LP 92": "52.00",
    "LAD": "30.00",
    "LSD": "35.30",
    "LK": "24.00",
    "LIK": "26.30",
    "FUR. 800": "23.10",
    "FUR 1500 (High)": "",
    "FUR. 1500 (Low)": "22.20"
  },
  {
    "Date": "20.05.2003",
    "LP 95": "55.00",
    "LP 92": "52.00",
    "LAD": "30.00",
    "LSD": "35.30",
    "LK": "24.00",
    "LIK": "26.30",
    "FUR. 800": "26.60",
    "FUR 1500 (High)": "",
    "FUR. 1500 (Low)": "25.70"
  },
  {
    "Date": "25.04.2003",
    "LP 95": "57.00",
    "LP 92": "54.00",
    "LAD": "30.00",
    "LSD": "35.30",
    "LK": "24.00",
    "LIK": "26.30",
    "FUR. 800": "26.60",
    "FUR 1500 (High)": "",
    "FUR. 1500 (Low)": "25.70"
  },
  {
    "Date": "26.03.2003",
    "LP 95": "56.00",
    "LP 92": "53.00",
    "LAD": "30.00",
    "LSD": "35.30",
    "LK": "24.00",
    "LIK": "26.30",
    "FUR. 800": "26.60",
    "FUR 1500 (High)": "",
    "FUR. 1500 (Low)": "25.70"
  },
  {
    "Date": "14.02.2003",
    "LP 95": "54.00",
    "LP 92": "51.00",
    "LAD": "30.00",
    "LSD": "35.30",
    "LK": "24.00",
    "LIK": "26.30",
    "FUR. 800": "25.60",
    "FUR 1500 (High)": "",
    "FUR. 1500 (Low)": "24.70"
  },
  {
    "Date": "16.01.2003",
    "LP 95": "52.00",
    "LP 92": "49.00",
    "LAD": "30.00",
    "LSD": "35.30",
    "LK": "24.00",
    "LIK": "26.30",
    "FUR. 800": "23.70",
    "FUR 1500 (High)": "",
    "FUR. 1500 (Low)": "22.70"
  },
  {
    "Date": "16.12.2002",
    "LP 95": "52.00",
    "LP 92": "49.00",
    "LAD": "30.00",
    "LSD": "35.30",
    "LK": "24.00",
    "LIK": "26.30",
    "FUR. 800": "21.90",
    "FUR 1500 (High)": "",
    "FUR. 1500 (Low)": "20.70"
  },
  {
    "Date": "15.10.2002",
    "LP 95": "52.00",
    "LP 92": "49.00",
    "LAD": "30.00",
    "LSD": "35.30",
    "LK": "24.00",
    "LIK": "26.30",
    "FUR. 800": "24.10",
    "FUR 1500 (High)": "",
    "FUR. 1500 (Low)": "23.00"
  },
  {
    "Date": "16.09.2002",
    "LP 95": "50.50",
    "LP 92": "47.50",
    "LAD": "28.50",
    "LSD": "33.80",
    "LK": "22.00",
    "LIK": "24.30",
    "FUR. 800": "23.00",
    "FUR 1500 (High)": "",
    "FUR. 1500 (Low)": "21.90"
  },
  {
    "Date": "15.08.2002",
    "LP 95": "50.50",
    "LP 92": "47.50",
    "LAD": "28.00",
    "LSD": "33.30",
    "LK": "21.00",
    "LIK": "23.30",
    "FUR. 800": "21.90",
    "FUR 1500 (High)": "",
    "FUR. 1500 (Low)": "21.20"
  },
  {
    "Date": "29.07.2002",
    "LP 95": "50.50",
    "LP 92": "47.50",
    "LAD": "27.50",
    "LSD": "32.80",
    "LK": "20.40",
    "LIK": "22.70",
    "FUR. 800": "20.90",
    "FUR 1500 (High)": "",
    "FUR. 1500 (Low)": "20.20"
  },
  {
    "Date": "15.07.2002",
    "LP 95": "50.50",
    "LP 92": "47.50",
    "LAD": "27.50",
    "LSD": "32.80",
    "LK": "20.50",
    "LIK": "22.80",
    "FUR. 800": "20.90",
    "FUR 1500 (High)": "",
    "FUR. 1500 (Low)": "20.20"
  },
  {
    "Date": "21.06.2002",
    "LP 95": "57.50",
    "LP 92": "54.50",
    "LAD": "30.50",
    "LSD": "35.30",
    "LK": "20.90",
    "LIK": "23.20",
    "FUR. 800": "21.40",
    "FUR 1500 (High)": "",
    "FUR. 1500 (Low)": "21.00"
  },
  {
    "Date": "21.05.2002",
    "LP 95": "57.00",
    "LP 92": "54.00",
    "LAD": "30.00",
    "LSD": "35.30",
    "LK": "20.90",
    "LIK": "23.20",
    "FUR. 800": "21.40",
    "FUR 1500 (High)": "",
    "FUR. 1500 (Low)": "20.00"
  },
  {
    "Date": "22.04.2002",
    "LP 95": "55.00",
    "LP 92": "52.00",
    "LAD": "28.00",
    "LSD": "33.30",
    "LK": "19.40",
    "LIK": "21.70",
    "FUR. 800": "19.40",
    "FUR 1500 (High)": "",
    "FUR. 1500 (Low)": "18.00"
  },
  {
    "Date": "22.03.2002",
    "LP 95": "53.00",
    "LP 92": "50.00",
    "LAD": "26.00",
    "LSD": "31.30",
    "LK": "17.40",
    "LIK": "19.70",
    "FUR. 800": "17.40",
    "FUR 1500 (High)": "",
    "FUR. 1500 (Low)": "16.00"
  },
  {
    "Date": "25.02.2002",
    "LP 95": "52.00",
    "LP 92": "49.00",
    "LAD": "26.00",
    "LSD": "31.30",
    "LK": "17.40",
    "LIK": "19.70",
    "FUR. 800": "17.00",
    "FUR 1500 (High)": "",
    "FUR. 1500 (Low)": "15.50"
  },
  {
    "Date": "28.12.2001",
    "LP 95": "53.00",
    "LP 92": "50.00",
    "LAD": "16.50",
    "LSD": "31.80",
    "LK": "17.40",
    "LIK": "19.70",
    "FUR. 800": "17.00",
    "FUR 1500 (High)": "",
    "FUR. 1500 (Low)": "15.80"
  },
  {
    "Date": "15.11.2001",
    "LP 95": "53.00",
    "LP 92": "50.00",
    "LAD": "27.50",
    "LSD": "32.80",
    "LK": "17.40",
    "LIK": "19.70",
    "FUR. 800": "17.00",
    "FUR 1500 (High)": "",
    "FUR. 1500 (Low)": "15.80"
  },
  {
    "Date": "15.04.2001",
    "LP 95": "53.00",
    "LP 92": "50.00",
    "LAD": "27.50",
    "LSD": "32.80",
    "LK": "19.40",
    "LIK": "21.70",
    "FUR. 800": "17.00",
    "FUR 1500 (High)": "",
    "FUR. 1500 (Low)": "15.80"
  },
  {
    "Date": "27.12.2000",
    "LP 95": "53.00",
    "LP 92": "50.00",
    "LAD": "24.50",
    "LSD": "29.80",
    "LK": "18.40",
    "LIK": "20.70",
    "FUR. 800": "15.10",
    "FUR 1500 (High)": "",
    "FUR. 1500 (Low)": "14.00"
  },
  {
    "Date": "16.11.2000",
    "LP 95": "53.00",
    "LP 92": "50.00",
    "LAD": "21.50",
    "LSD": "26.80",
    "LK": "17.40",
    "LIK": "19.70",
    "FUR. 800": "13.70",
    "FUR 1500 (High)": "",
    "FUR. 1500 (Low)": "12.70"
  },
  {
    "Date": "12.06.2000",
    "LP 95": "53.00",
    "LP 92": "50.00",
    "LAD": "19.50",
    "LSD": "24.80",
    "LK": "15.40",
    "LIK": "17.70",
    "FUR. 800": "10.50",
    "FUR 1500 (High)": "",
    "FUR. 1500 (Low)": "9.80"
  },
  {
    "Date": "07.02.2000",
    "LP 95": "53.00",
    "LP 92": "50.00",
    "LAD": "16.20",
    "LSD": "21.50",
    "LK": "15.40",
    "LIK": "17.70",
    "FUR. 800": "7.50",
    "FUR 1500 (High)": "",
    "FUR. 1500 (Low)": "6.80"
  },
  {
    "Date": "26.05.1999",
    "LP 95": "53.00",
    "LP 92": "50.00",
    "LAD": "13.20",
    "LSD": "18.50",
    "LK": "10.40",
    "LIK": "12.70",
    "FUR. 800": "7.50",
    "FUR 1500 (High)": "",
    "FUR. 1500 (Low)": "6.80"
  },
  {
    "Date": "28.09.1996",
    "LP 95": "55.00",
    "LP 92": "50.00",
    "LAD": "13.20",
    "LSD": "18.50",
    "LK": "10.40",
    "LIK": "12.70",
    "FUR. 800": "7.50",
    "FUR 1500 (High)": "",
    "FUR. 1500 (Low)": "6.80"
  },
  {
    "Date": "09.02.1995",
    "LP 95": "42.50",
    "LP 92": "40.00",
    "LAD": "12.40",
    "LSD": "15.20",
    "LK": "9.50",
    "LIK": "11.80",
    "FUR. 800": "6.25",
    "FUR 1500 (High)": "",
    "FUR. 1500 (Low)": "5.55"
  },
  {
    "Date": "26.01.1995",
    "LP 95": "42.50",
    "LP 92": "40.00",
    "LAD": "11.40",
    "LSD": "14.20",
    "LK": "9.50",
    "LIK": "11.80",
    "FUR. 800": "6.25",
    "FUR 1500 (High)": "",
    "FUR. 1500 (Low)": "5.55"
  },
  {
    "Date": "28.06.1994",
    "LP 95": "37.50",
    "LP 92": "35.00",
    "LAD": "11.40",
    "LSD": "14.20",
    "LK": "9.50",
    "LIK": "11.80",
    "FUR. 800": "6.25",
    "FUR 1500 (High)": "",
    "FUR. 1500 (Low)": "5.55"
  },
  {
    "Date": "28.03.1994",
    "LP 95": "37.50",
    "LP 92": "35.00",
    "LAD": "12.40",
    "LSD": "12.20",
    "LK": "11.80",
    "LIK": "11.80",
    "FUR. 800": "6.25",
    "FUR 1500 (High)": "",
    "FUR. 1500 (Low)": "5.55"
  },
  {
    "Date": "17.02.1994",
    "LP 95": "37.50",
    "LP 92": "35.00",
    "LAD": "12.30",
    "LSD": "15.10",
    "LK": "11.80",
    "LIK": "11.80",
    "FUR. 800": "6.25",
    "FUR 1500 (High)": "",
    "FUR. 1500 (Low)": "5.55"
  },
  {
    "Date": "17.12.1993",
    "LP 95": "37.50",
    "LP 92": "35.00",
    "LAD": "12.20",
    "LSD": "15.00",
    "LK": "11.80",
    "LIK": "11.80",
    "FUR. 800": "6.25",
    "FUR 1500 (High)": "",
    "FUR. 1500 (Low)": "5.55"
  },
  {
    "Date": "14.10.1993",
    "LP 95": "37.50",
    "LP 92": "35.00",
    "LAD": "12.00",
    "LSD": "14.80",
    "LK": "11.80",
    "LIK": "11.80",
    "FUR. 800": "6.25",
    "FUR 1500 (High)": "",
    "FUR. 1500 (Low)": "5.55"
  },
  {
    "Date": "30.08.1993",
    "LP 95": "35.50",
    "LP 92": "33.00",
    "LAD": "11.90",
    "LSD": "14.70",
    "LK": "11.80",
    "LIK": "11.80",
    "FUR. 800": "6.25",
    "FUR 1500 (High)": "",
    "FUR. 1500 (Low)": "5.55"
  },
  {
    "Date": "12.07.1993",
    "LP 95": "35.50",
    "LP 92": "33.00",
    "LAD": "11.80",
    "LSD": "14.60",
    "LK": "11.80",
    "LIK": "11.80",
    "FUR. 800": "6.25",
    "FUR 1500 (High)": "",
    "FUR. 1500 (Low)": "5.55"
  },
  {
    "Date": "11.06.1993",
    "LP 95": "35.50",
    "LP 92": "33.00",
    "LAD": "11.70",
    "LSD": "14.50",
    "LK": "11.80",
    "LIK": "11.80",
    "FUR. 800": "6.25",
    "FUR 1500 (High)": "",
    "FUR. 1500 (Low)": "5.55"
  },
  {
    "Date": "07.06.1993",
    "LP 95": "35.50",
    "LP 92": "33.00",
    "LAD": "11.70",
    "LSD": "14.50",
    "LK": "8.80",
    "LIK": "9.85",
    "FUR. 800": "6.25",
    "FUR 1500 (High)": "",
    "FUR. 1500 (Low)": "5.55"
  },
  {
    "Date": "21.12.1992",
    "LP 95": "35.50",
    "LP 92": "33.00",
    "LAD": "11.65",
    "LSD": "14.50",
    "LK": "8.80",
    "LIK": "9.85",
    "FUR. 800": "6.25",
    "FUR 1500 (High)": "",
    "FUR. 1500 (Low)": "5.55"
  },
  {
    "Date": "03.10.1992",
    "LP 95": "35.50",
    "LP 92": "33.00",
    "LAD": "11.60",
    "LSD": "14.5",
    "LK": "8.80",
    "LIK": "9.85",
    "FUR. 800": "6.25",
    "FUR 1500 (High)": "",
    "FUR. 1500 (Low)": "5.55"
  },
  {
    "Date": "21.08.1992",
    "LP 95": "35.50",
    "LP 92": "33.00",
    "LAD": "11.55",
    "LSD": "14.50",
    "LK": "8.80",
    "LIK": "9.85",
    "FUR. 800": "6.25",
    "FUR 1500 (High)": "",
    "FUR. 1500 (Low)": "5.55"
  },
  {
    "Date": "14.07.1992",
    "LP 95": "32.50",
    "LP 92": "30.00",
    "LAD": "11.55",
    "LSD": "14.50",
    "LK": "8.80",
    "LIK": "9.85",
    "FUR. 800": "6.25",
    "FUR 1500 (High)": "",
    "FUR. 1500 (Low)": "5.55"
  },
  {
    "Date": "28.06.1992",
    "LP 95": "32.50",
    "LP 92": "30.00",
    "LAD": "11.50",
    "LSD": "14.50",
    "LK": "8.80",
    "LIK": "9.85",
    "FUR. 800": "6.25",
    "FUR 1500 (High)": "",
    "FUR. 1500 (Low)": "5.55"
  },
  {
    "Date": "13.05.1992",
    "LP 95": "32.50",
    "LP 92": "30.00",
    "LAD": "11.50",
    "LSD": "13.50",
    "LK": "8.80",
    "LIK": "9.85",
    "FUR. 800": "6.25",
    "FUR 1500 (High)": "",
    "FUR. 1500 (Low)": "5.55"
  },
  {
    "Date": "01.01.1991",
    "LP 95": "32.50",
    "LP 92": "30.00",
    "LAD": "11.00",
    "LSD": "13.00",
    "LK": "8.80",
    "LIK": "9.85",
    "FUR. 800": "6.25",
    "FUR 1500 (High)": "",
    "FUR. 1500 (Low)": "5.55"
  },
  {
    "Date": "26.12.1990",
    "LP 95": "32.50",
    "LP 92": "30.00",
    "LAD": "11.00",
    "LSD": "13.00",
    "LK": "8.80",
    "LIK": "9.85",
    "FUR. 800": "6.30",
    "FUR 1500 (High)": "",
    "FUR. 1500 (Low)": "5.60"
  },
  {
    "Date": "05.11.1990",
    "LP 95": "38.00",
    "LP 92": "35.00",
    "LAD": "13.00",
    "LSD": "15.00",
    "LK": "8.80",
    "LIK": "9.58",
    "FUR. 800": "6.30",
    "FUR 1500 (High)": "",
    "FUR. 1500 (Low)": "5.60"
  },
  {
    "Date": "14.08.1990",
    "LP 95": "27.00",
    "LP 92": "25.00",
    "LAD": "11.00",
    "LSD": "12.50",
    "LK": "8.00",
    "LIK": "9.85",
    "FUR. 800": "5.40",
    "FUR 1500 (High)": "",
    "FUR. 1500 (Low)": "4.90"
  },
  {
    "Date": "01.03.1990",
    "LP 95": "22.00",
    "LP 92": "20.00",
    "LAD": "9.60",
    "LSD": "10.90",
    "LK": "6.58",
    "LIK": "9.85",
    "FUR. 800": "4.70",
    "FUR 1500 (High)": "",
    "FUR. 1500 (Low)": "4.29"
  }
]